{
  "info": {
    "name": "VeraMarket Sprints 1, 2 & 3 API",
    "description": "Colección completa de endpoints para Sprints 1 al 3 del proyecto VeraMarket. Incluye scripts automáticos de inyección de variables entre peticiones.",
    "schema": "https://schema.getpostman.com/json/collection/v2.1.0/collection.json"
  },
  "item": [
    {
      "name": "0. Health",
      "item": [
        {
          "name": "Health Check",
          "event": [
            {
              "listen": "test",
              "script": {
                "exec": [
                  "pm.test('Servicio activo', function () {",
                  "    pm.response.to.have.status(200);",
                  "    var json = pm.response.json();",
                  "    pm.expect(json.status).to.eql('ok');",
                  "});"
                ],
                "type": "text/javascript"
              }
            }
          ],
          "request": {
            "method": "GET",
            "header": [],
            "url": {
              "raw": "{{base_url}}/health",
              "host": ["{{base_url}}"],
              "path": ["health"]
            }
          }
        }
      ]
    },
    {
      "name": "1. Auth (Sprint 1 - EP-01)",
      "description": "Flujo de autenticación OTP: solicitar código → verificar → completar perfil → solicitar rol vendedor.",
      "item": [
        {
          "name": "1.1 Solicitar OTP",
          "event": [
            {
              "listen": "test",
              "script": {
                "exec": [
                  "pm.test('OTP enviado correctamente', function () {",
                  "    pm.response.to.have.status(200);",
                  "    var json = pm.response.json();",
                  "    pm.expect(json.email).to.eql(pm.environment.get('test_email'));",
                  "});"
                ],
                "type": "text/javascript"
              }
            }
          ],
          "request": {
            "method": "POST",
            "header": [
              { "key": "Content-Type", "value": "application/json" }
            ],
            "body": {
              "mode": "raw",
              "raw": "{\n  \"email\": \"{{test_email}}\"\n}"
            },
            "url": {
              "raw": "{{base_url}}/api/v1/auth/otp/request",
              "host": ["{{base_url}}"],
              "path": ["api", "v1", "auth", "otp", "request"]
            }
          }
        },
        {
          "name": "1.2 Verificar OTP",
          "event": [
            {
              "listen": "test",
              "script": {
                "exec": [
                  "pm.test('Token JWT recibido', function () {",
                  "    pm.response.to.have.status(200);",
                  "    var json = pm.response.json();",
                  "    pm.expect(json.access_token).to.be.a('string');",
                  "    pm.environment.set('token', json.access_token);",
                  "});"
                ],
                "type": "text/javascript"
              }
            }
          ],
          "request": {
            "method": "POST",
            "header": [
              { "key": "Content-Type", "value": "application/json" }
            ],
            "body": {
              "mode": "raw",
              "raw": "{\n  \"email\": \"{{test_email}}\",\n  \"code\": \"{{otp_code}}\"\n}"
            },
            "url": {
              "raw": "{{base_url}}/api/v1/auth/otp/verify",
              "host": ["{{base_url}}"],
              "path": ["api", "v1", "auth", "otp", "verify"]
            }
          }
        },
        {
          "name": "1.3 Completar Perfil",
          "event": [
            {
              "listen": "test",
              "script": {
                "exec": [
                  "pm.test('Perfil completado', function () {",
                  "    pm.response.to.have.status(200);",
                  "    var json = pm.response.json();",
                  "    pm.expect(json.id).to.be.a('string');",
                  "    pm.environment.set('user_id', json.id);",
                  "});"
                ],
                "type": "text/javascript"
              }
            }
          ],
          "request": {
            "method": "POST",
            "header": [
              { "key": "Content-Type", "value": "application/json" },
              { "key": "Authorization", "value": "Bearer {{token}}" }
            ],
            "body": {
              "mode": "raw",
              "raw": "{\n  \"name\": \"Vendedor Demo\",\n  \"institutional_id\": \"2021001234\",\n  \"phone\": \"3001234567\",\n  \"accept_terms\": true\n}"
            },
            "url": {
              "raw": "{{base_url}}/api/v1/auth/profile/complete",
              "host": ["{{base_url}}"],
              "path": ["api", "v1", "auth", "profile", "complete"]
            }
          }
        },
        {
          "name": "1.4 Actualizar Perfil",
          "event": [
            {
              "listen": "test",
              "script": {
                "exec": [
                  "pm.test('Perfil actualizado', function () {",
                  "    pm.response.to.have.status(200);",
                  "});"
                ],
                "type": "text/javascript"
              }
            }
          ],
          "request": {
            "method": "PUT",
            "header": [
              { "key": "Content-Type", "value": "application/json" },
              { "key": "Authorization", "value": "Bearer {{token}}" }
            ],
            "body": {
              "mode": "raw",
              "raw": "{\n  \"name\": \"Vendedor Actualizado\",\n  \"phone\": \"3109876543\"\n}"
            },
            "url": {
              "raw": "{{base_url}}/api/v1/auth/profile",
              "host": ["{{base_url}}"],
              "path": ["api", "v1", "auth", "profile"]
            }
          }
        },
        {
          "name": "1.5 Solicitar Rol Vendedor (Sinapsis)",
          "event": [
            {
              "listen": "test",
              "script": {
                "exec": [
                  "pm.test('Rol de vendedor obtenido', function () {",
                  "    pm.response.to.have.status(200);",
                  "    var json = pm.response.json();",
                  "    pm.expect(json.role).to.eql('vendedor');",
                  "});"
                ],
                "type": "text/javascript"
              }
            }
          ],
          "request": {
            "method": "POST",
            "header": [
              { "key": "Content-Type", "value": "application/json" },
              { "key": "Authorization", "value": "Bearer {{token}}" }
            ],
            "body": {
              "mode": "raw",
              "raw": "{\n  \"sinapsis_code\": \"{{sinapsis_code}}\"\n}"
            },
            "url": {
              "raw": "{{base_url}}/api/v1/auth/vendor/request",
              "host": ["{{base_url}}"],
              "path": ["api", "v1", "auth", "vendor", "request"]
            }
          }
        }
      ]
    },
    {
      "name": "2. Users & Privacy (Sprint 1 - EP-01)",
      "description": "Gestión de perfil propio, perfil público de terceros y configuración de privacidad.",
      "item": [
        {
          "name": "2.1 Mi Perfil (Privado)",
          "event": [
            {
              "listen": "test",
              "script": {
                "exec": [
                  "pm.test('Perfil privado obtenido', function () {",
                  "    pm.response.to.have.status(200);",
                  "    var json = pm.response.json();",
                  "    pm.expect(json.email).to.be.a('string');",
                  "    pm.environment.set('user_id', json.id);",
                  "});"
                ],
                "type": "text/javascript"
              }
            }
          ],
          "request": {
            "method": "GET",
            "header": [
              { "key": "Authorization", "value": "Bearer {{token}}" }
            ],
            "url": {
              "raw": "{{base_url}}/api/v1/users/me",
              "host": ["{{base_url}}"],
              "path": ["api", "v1", "users", "me"]
            }
          }
        },
        {
          "name": "2.2 Perfil Público (por ID)",
          "event": [
            {
              "listen": "test",
              "script": {
                "exec": [
                  "pm.test('Perfil público obtenido', function () {",
                  "    pm.response.to.have.status(200);",
                  "});"
                ],
                "type": "text/javascript"
              }
            }
          ],
          "request": {
            "method": "GET",
            "header": [],
            "url": {
              "raw": "{{base_url}}/api/v1/users/{{user_id}}",
              "host": ["{{base_url}}"],
              "path": ["api", "v1", "users", "{{user_id}}"]
            }
          }
        },
        {
          "name": "2.3 Obtener Config. Privacidad",
          "event": [
            {
              "listen": "test",
              "script": {
                "exec": [
                  "pm.test('Config privacidad obtenida', function () {",
                  "    pm.response.to.have.status(200);",
                  "    var json = pm.response.json();",
                  "    pm.expect(json).to.have.property('show_email');",
                  "    pm.expect(json).to.have.property('show_phone');",
                  "});"
                ],
                "type": "text/javascript"
              }
            }
          ],
          "request": {
            "method": "GET",
            "header": [
              { "key": "Authorization", "value": "Bearer {{token}}" }
            ],
            "url": {
              "raw": "{{base_url}}/api/v1/users/me/privacy",
              "host": ["{{base_url}}"],
              "path": ["api", "v1", "users", "me", "privacy"]
            }
          }
        },
        {
          "name": "2.4 Actualizar Config. Privacidad",
          "event": [
            {
              "listen": "test",
              "script": {
                "exec": [
                  "pm.test('Privacidad actualizada', function () {",
                  "    pm.response.to.have.status(200);",
                  "    var json = pm.response.json();",
                  "    pm.expect(json.show_email).to.eql(true);",
                  "    pm.expect(json.show_phone).to.eql(false);",
                  "});"
                ],
                "type": "text/javascript"
              }
            }
          ],
          "request": {
            "method": "PUT",
            "header": [
              { "key": "Content-Type", "value": "application/json" },
              { "key": "Authorization", "value": "Bearer {{token}}" }
            ],
            "body": {
              "mode": "raw",
              "raw": "{\n  \"show_email\": true,\n  \"show_phone\": false\n}"
            },
            "url": {
              "raw": "{{base_url}}/api/v1/users/me/privacy",
              "host": ["{{base_url}}"],
              "path": ["api", "v1", "users", "me", "privacy"]
            }
          }
        }
      ]
    },
    {
      "name": "3. Catálogo P2P (Sprint 3 - EP-03)",
      "description": "CRUD completo de productos: crear, listar, obtener, editar, alternar estado y soft-delete.",
      "item": [
        {
          "name": "3.1 Crear Producto",
          "event": [
            {
              "listen": "test",
              "script": {
                "exec": [
                  "pm.test('Producto creado', function () {",
                  "    pm.response.to.have.status(201);",
                  "    var json = pm.response.json();",
                  "    pm.expect(json.id).to.be.a('string');",
                  "    pm.environment.set('product_id', json.id);",
                  "});"
                ],
                "type": "text/javascript"
              }
            }
          ],
          "request": {
            "method": "POST",
            "header": [
              { "key": "Content-Type", "value": "application/json" },
              { "key": "Authorization", "value": "Bearer {{token}}" }
            ],
            "body": {
              "mode": "raw",
              "raw": "{\n  \"name\": \"Audífonos Bluetooth\",\n  \"description\": \"Poco uso, excelentes bajos. Campus UAO.\",\n  \"price\": 50000,\n  \"category\": \"tecnologia\",\n  \"image_urls\": [\"https://ejemplo.com/audifonos.jpg\"]\n}"
            },
            "url": {
              "raw": "{{base_url}}/api/v1/products/",
              "host": ["{{base_url}}"],
              "path": ["api", "v1", "products", ""]
            }
          }
        },
        {
          "name": "3.2 Listar Productos",
          "event": [
            {
              "listen": "test",
              "script": {
                "exec": [
                  "pm.test('Lista de productos obtenida', function () {",
                  "    pm.response.to.have.status(200);",
                  "    pm.expect(pm.response.json()).to.be.an('array');",
                  "});"
                ],
                "type": "text/javascript"
              }
            }
          ],
          "request": {
            "method": "GET",
            "header": [],
            "url": {
              "raw": "{{base_url}}/api/v1/products/?limit=20&offset=0",
              "host": ["{{base_url}}"],
              "path": ["api", "v1", "products", ""],
              "query": [
                { "key": "limit", "value": "20" },
                { "key": "offset", "value": "0" }
              ]
            }
          }
        },
        {
          "name": "3.3 Listar Productos por Categoría",
          "event": [
            {
              "listen": "test",
              "script": {
                "exec": [
                  "pm.test('Filtro por categoría funciona', function () {",
                  "    pm.response.to.have.status(200);",
                  "    pm.expect(pm.response.json()).to.be.an('array');",
                  "});"
                ],
                "type": "text/javascript"
              }
            }
          ],
          "request": {
            "method": "GET",
            "header": [],
            "url": {
              "raw": "{{base_url}}/api/v1/products/?category=tecnologia",
              "host": ["{{base_url}}"],
              "path": ["api", "v1", "products", ""],
              "query": [
                { "key": "category", "value": "tecnologia" }
              ]
            }
          }
        },
        {
          "name": "3.4 Obtener Producto por ID",
          "event": [
            {
              "listen": "test",
              "script": {
                "exec": [
                  "pm.test('Producto obtenido', function () {",
                  "    pm.response.to.have.status(200);",
                  "    var json = pm.response.json();",
                  "    pm.expect(json.id).to.eql(pm.environment.get('product_id'));",
                  "});"
                ],
                "type": "text/javascript"
              }
            }
          ],
          "request": {
            "method": "GET",
            "header": [],
            "url": {
              "raw": "{{base_url}}/api/v1/products/{{product_id}}",
              "host": ["{{base_url}}"],
              "path": ["api", "v1", "products", "{{product_id}}"]
            }
          }
        },
        {
          "name": "3.5 Editar Producto",
          "event": [
            {
              "listen": "test",
              "script": {
                "exec": [
                  "pm.test('Producto editado', function () {",
                  "    pm.response.to.have.status(200);",
                  "    var json = pm.response.json();",
                  "    pm.expect(json.name).to.eql('Audífonos Bluetooth Sony');",
                  "});"
                ],
                "type": "text/javascript"
              }
            }
          ],
          "request": {
            "method": "PUT",
            "header": [
              { "key": "Content-Type", "value": "application/json" },
              { "key": "Authorization", "value": "Bearer {{token}}" }
            ],
            "body": {
              "mode": "raw",
              "raw": "{\n  \"name\": \"Audífonos Bluetooth Sony\",\n  \"price\": 45000\n}"
            },
            "url": {
              "raw": "{{base_url}}/api/v1/products/{{product_id}}",
              "host": ["{{base_url}}"],
              "path": ["api", "v1", "products", "{{product_id}}"]
            }
          }
        },
        {
          "name": "3.6 Alternar Estado (Pausar/Activar)",
          "event": [
            {
              "listen": "test",
              "script": {
                "exec": [
                  "pm.test('Estado alternado', function () {",
                  "    pm.response.to.have.status(200);",
                  "    var json = pm.response.json();",
                  "    pm.expect(json).to.have.property('is_active');",
                  "});"
                ],
                "type": "text/javascript"
              }
            }
          ],
          "request": {
            "method": "PATCH",
            "header": [
              { "key": "Authorization", "value": "Bearer {{token}}" }
            ],
            "url": {
              "raw": "{{base_url}}/api/v1/products/{{product_id}}/status",
              "host": ["{{base_url}}"],
              "path": ["api", "v1", "products", "{{product_id}}", "status"]
            }
          }
        },
        {
          "name": "3.7 Eliminar Producto (Soft-Delete)",
          "event": [
            {
              "listen": "test",
              "script": {
                "exec": [
                  "pm.test('Producto eliminado (soft-delete)', function () {",
                  "    pm.response.to.have.status(200);",
                  "    var json = pm.response.json();",
                  "    pm.expect(json.message).to.include('exitosamente');",
                  "});"
                ],
                "type": "text/javascript"
              }
            }
          ],
          "request": {
            "method": "DELETE",
            "header": [
              { "key": "Authorization", "value": "Bearer {{token}}" }
            ],
            "url": {
              "raw": "{{base_url}}/api/v1/products/{{product_id}}",
              "host": ["{{base_url}}"],
              "path": ["api", "v1", "products", "{{product_id}}"]
            }
          }
        }
      ]
    },
    {
      "name": "4. Push Notifications (Sprint 2 - EP-02)",
      "description": "Suscripción a notificaciones push vía Service Worker.",
      "item": [
        {
          "name": "4.1 Suscribir Push",
          "event": [
            {
              "listen": "test",
              "script": {
                "exec": [
                  "pm.test('Suscripción guardada', function () {",
                  "    pm.response.to.have.status(200);",
                  "    var json = pm.response.json();",
                  "    pm.expect(json.message).to.include('guardada');",
                  "});"
                ],
                "type": "text/javascript"
              }
            }
          ],
          "request": {
            "method": "POST",
            "header": [
              { "key": "Content-Type", "value": "application/json" },
              { "key": "Authorization", "value": "Bearer {{token}}" }
            ],
            "body": {
              "mode": "raw",
              "raw": "{\n  \"endpoint\": \"https://fcm.googleapis.com/fcm/send/demo-endpoint-12345\",\n  \"keys\": {\n    \"p256dh\": \"demo-p256dh-key\",\n    \"auth\": \"demo-auth-key\"\n  }\n}"
            },
            "url": {
              "raw": "{{base_url}}/api/v1/push/subscribe",
              "host": ["{{base_url}}"],
              "path": ["api", "v1", "push", "subscribe"]
            }
          }
        }
      ]
    },
    {
      "name": "5. Sprint 3 Híbrido (Búsqueda + Geo)",
      "description": "Pruebas de cuota diaria, ubicación vendedor y búsqueda híbrida con fallback.",
      "item": [
        {
          "name": "5.1 Obtener Cuota Diaria",
          "event": [
            {
              "listen": "test",
              "script": {
                "exec": [
                  "pm.test('Cuota diaria disponible', function () {",
                  "    pm.response.to.have.status(200);",
                  "    var json = pm.response.json();",
                  "    pm.expect(json).to.have.property('daily_limit');",
                  "    pm.expect(json).to.have.property('searches_used');",
                  "    pm.expect(json).to.have.property('remaining');",
                  "    pm.environment.set('quota_remaining', String(json.remaining));",
                  "});"
                ],
                "type": "text/javascript"
              }
            }
          ],
          "request": {
            "method": "GET",
            "header": [
              { "key": "Authorization", "value": "Bearer {{token}}" }
            ],
            "url": {
              "raw": "{{base_url}}/api/v1/users/me/search-quota",
              "host": ["{{base_url}}"],
              "path": ["api", "v1", "users", "me", "search-quota"]
            }
          }
        },
        {
          "name": "5.2 Configurar Ubicación Vendedor",
          "event": [
            {
              "listen": "test",
              "script": {
                "exec": [
                  "pm.test('Ubicación guardada', function () {",
                  "    pm.response.to.have.status(200);",
                  "    var json = pm.response.json();",
                  "    pm.expect(json).to.have.property('lat');",
                  "    pm.expect(json).to.have.property('lng');",
                  "    pm.environment.set('search_lat', String(json.lat));",
                  "    pm.environment.set('search_lng', String(json.lng));",
                  "    pm.environment.set('location_label', json.label || '');",
                  "});"
                ],
                "type": "text/javascript"
              }
            }
          ],
          "request": {
            "method": "PUT",
            "header": [
              { "key": "Content-Type", "value": "application/json" },
              { "key": "Authorization", "value": "Bearer {{token}}" }
            ],
            "body": {
              "mode": "raw",
              "raw": "{\n  \"lat\": {{search_lat}},\n  \"lng\": {{search_lng}},\n  \"campus\": \"UAO\",\n  \"label\": \"{{location_label}}\"\n}"
            },
            "url": {
              "raw": "{{base_url}}/api/v1/locations/me",
              "host": ["{{base_url}}"],
              "path": ["api", "v1", "locations", "me"]
            }
          }
        },
        {
          "name": "5.3 Obtener Ubicación Vendedor",
          "event": [
            {
              "listen": "test",
              "script": {
                "exec": [
                  "pm.test('Ubicación consultada', function () {",
                  "    pm.response.to.have.status(200);",
                  "    var json = pm.response.json();",
                  "    if (json) {",
                  "        pm.expect(json).to.have.property('lat');",
                  "        pm.expect(json).to.have.property('lng');",
                  "        pm.environment.set('search_lat', String(json.lat));",
                  "        pm.environment.set('search_lng', String(json.lng));",
                  "    }",
                  "});"
                ],
                "type": "text/javascript"
              }
            }
          ],
          "request": {
            "method": "GET",
            "header": [
              { "key": "Authorization", "value": "Bearer {{token}}" }
            ],
            "url": {
              "raw": "{{base_url}}/api/v1/locations/me",
              "host": ["{{base_url}}"],
              "path": ["api", "v1", "locations", "me"]
            }
          }
        },
        {
          "name": "5.4 Búsqueda Semántica Autenticada",
          "event": [
            {
              "listen": "test",
              "script": {
                "exec": [
                  "pm.test('Busqueda semántica/fallback autenticada', function () {",
                  "    pm.response.to.have.status(200);",
                  "    var json = pm.response.json();",
                  "    pm.expect(json).to.have.property('items');",
                  "    pm.expect(json).to.have.property('meta');",
                  "    pm.expect(json.items).to.be.an('array');",
                  "    pm.expect(json.meta).to.have.property('search_mode');",
                  "    if (json.meta.quota_remaining !== null) {",
                  "        pm.environment.set('quota_remaining', String(json.meta.quota_remaining));",
                  "    }",
                  "    pm.environment.set('search_mode_last', String(json.meta.search_mode));",
                  "});"
                ],
                "type": "text/javascript"
              }
            }
          ],
          "request": {
            "method": "GET",
            "header": [
              { "key": "Authorization", "value": "Bearer {{token}}" }
            ],
            "url": {
              "raw": "{{base_url}}/api/v1/products/search?q={{search_query_semantic}}&limit=20",
              "host": ["{{base_url}}"],
              "path": ["api", "v1", "products", "search"],
              "query": [
                { "key": "q", "value": "{{search_query_semantic}}" },
                { "key": "limit", "value": "20" }
              ]
            }
          }
        },
        {
          "name": "5.5 Búsqueda Full-Text Forzada",
          "event": [
            {
              "listen": "test",
              "script": {
                "exec": [
                  "pm.test('Busqueda full-text forzada', function () {",
                  "    pm.response.to.have.status(200);",
                  "    var json = pm.response.json();",
                  "    pm.expect(json).to.have.property('meta');",
                  "    pm.expect(json.meta).to.have.property('search_mode');",
                  "    pm.expect(json.meta.search_mode).to.not.eql('semantic');",
                  "    pm.environment.set('search_mode_last', String(json.meta.search_mode));",
                  "});"
                ],
                "type": "text/javascript"
              }
            }
          ],
          "request": {
            "method": "GET",
            "header": [
              { "key": "Authorization", "value": "Bearer {{token}}" }
            ],
            "url": {
              "raw": "{{base_url}}/api/v1/products/search?q={{search_query_fulltext}}&use_semantic=false&limit=20",
              "host": ["{{base_url}}"],
              "path": ["api", "v1", "products", "search"],
              "query": [
                { "key": "q", "value": "{{search_query_fulltext}}" },
                { "key": "use_semantic", "value": "false" },
                { "key": "limit", "value": "20" }
              ]
            }
          }
        },
        {
          "name": "5.6 Búsqueda Geo por Radio",
          "event": [
            {
              "listen": "test",
              "script": {
                "exec": [
                  "pm.test('Busqueda geoespacial por radio', function () {",
                  "    pm.response.to.have.status(200);",
                  "    var json = pm.response.json();",
                  "    var radius = parseFloat(pm.environment.get('search_radius') || '300');",
                  "    pm.expect(json.items).to.be.an('array');",
                  "    json.items.forEach(function (item) {",
                  "        if (item.distance_meters !== null && item.distance_meters !== undefined) {",
                  "            pm.expect(item.distance_meters).to.be.below(radius + 1);",
                  "        }",
                  "    });",
                  "});"
                ],
                "type": "text/javascript"
              }
            }
          ],
          "request": {
            "method": "GET",
            "header": [
              { "key": "Authorization", "value": "Bearer {{token}}" }
            ],
            "url": {
              "raw": "{{base_url}}/api/v1/products/search?q={{search_query_semantic}}&lat={{search_lat}}&lng={{search_lng}}&radius_meters={{search_radius}}&limit=50",
              "host": ["{{base_url}}"],
              "path": ["api", "v1", "products", "search"],
              "query": [
                { "key": "q", "value": "{{search_query_semantic}}" },
                { "key": "lat", "value": "{{search_lat}}" },
                { "key": "lng", "value": "{{search_lng}}" },
                { "key": "radius_meters", "value": "{{search_radius}}" },
                { "key": "limit", "value": "50" }
              ]
            }
          }
        },
        {
          "name": "5.7 Fallback sin Token",
          "event": [
            {
              "listen": "test",
              "script": {
                "exec": [
                  "pm.test('Fallback para usuario no autenticado', function () {",
                  "    pm.response.to.have.status(200);",
                  "    var json = pm.response.json();",
                  "    pm.expect(json.meta.search_mode).to.eql('fallback_fulltext');",
                  "    pm.expect(json.meta.reason).to.eql('unauthenticated');",
                  "});"
                ],
                "type": "text/javascript"
              }
            }
          ],
          "request": {
            "method": "GET",
            "header": [],
            "url": {
              "raw": "{{base_url}}/api/v1/products/search?q={{search_query_semantic}}&limit=20",
              "host": ["{{base_url}}"],
              "path": ["api", "v1", "products", "search"],
              "query": [
                { "key": "q", "value": "{{search_query_semantic}}" },
                { "key": "limit", "value": "20" }
              ]
            }
          }
        },
        {
          "name": "5.8 Eliminar Ubicación Vendedor",
          "event": [
            {
              "listen": "test",
              "script": {
                "exec": [
                  "pm.test('Ubicación eliminada o no existente', function () {",
                  "    pm.response.to.have.status(200);",
                  "    var json = pm.response.json();",
                  "    pm.expect(json).to.have.property('deleted');",
                  "});"
                ],
                "type": "text/javascript"
              }
            }
          ],
          "request": {
            "method": "DELETE",
            "header": [
              { "key": "Authorization", "value": "Bearer {{token}}" }
            ],
            "url": {
              "raw": "{{base_url}}/api/v1/locations/me",
              "host": ["{{base_url}}"],
              "path": ["api", "v1", "locations", "me"]
            }
          }
        }
      ]
    }
  ]
}
